README.rst
setup.py
meepo2/__init__.py
meepo2/_compat.py
meepo2/signals.py
meepo2/utils.py
meepo2.egg-info/PKG-INFO
meepo2.egg-info/SOURCES.txt
meepo2.egg-info/dependency_links.txt
meepo2.egg-info/not-zip-safe
meepo2.egg-info/requires.txt
meepo2.egg-info/top_level.txt
meepo2/apps/__init__.py
meepo2/apps/eventsourcing/__init__.py
meepo2/apps/eventsourcing/event_store.py
meepo2/apps/eventsourcing/prepare_commit.py
meepo2/apps/eventsourcing/pub.py
meepo2/apps/eventsourcing/sub.py
meepo2/apps/replicator/__init__.py
meepo2/apps/replicator/queue.py
meepo2/apps/replicator/rq.py
meepo2/apps/replicator/utils.py
meepo2/apps/replicator/worker.py
meepo2/pub/__init__.py
meepo2/pub/mysql.py
meepo2/pub/sqlalchemy.py
meepo2/sub/__init__.py
meepo2/sub/dummy.py
meepo2/sub/nano.py
meepo2/sub/statsd.py
meepo2/sub/zmq.py