Metadata-Version: 2.1
Name: meepo2
Version: 0.2.5
Summary: event sourcing for databases.
Home-page: https://github.com/huskar-org/meepo2
Author: Lx Yu
Author-email: i@lxyu.net
License: MIT
Keywords: eventsourcing event sourcing replication cache elasticsearch
Platform: UNKNOWN
Classifier: Topic :: Software Development
Classifier: Development Status :: 3 - Alpha
Classifier: Intended Audience :: Developers
Classifier: License :: OSI Approved :: MIT License
Classifier: Programming Language :: Python :: 2.7
Classifier: Programming Language :: Python :: 3.3
Classifier: Programming Language :: Python :: 3.4
Classifier: Programming Language :: Python :: Implementation :: CPython
Classifier: Programming Language :: Python :: Implementation :: PyPy
Provides-Extra: dev
